[
  {
    "id": 1,
    "name": "Liam",
    "points": 4
  },
  {
    "id": 2,
    "name": "Cole",
    "points": 5
  },
  {
    "id": 3,
    "name": "Jarrod",
    "points": 6,
    "wins": 3,
    "loses": 1
  },
  {
    "name": {
      "inputName": "Ethan"
    },
    "points": {
      "inputPoints": "7"
    },
    "wins": {
      "inputWins": "3"
    }
  },
  {
    "name": {
      "name": "sam"
    },
    "points": {
      "points": "100"
    },
    "wins": {
      "wins": "1"
    }
  },
  {
    "name": {
      "name": "loventia"
    },
    "points": {
      "points": "100"
    },
    "wins": {
      "wins": "123"
    }
  }
]